swedish_market_insights/__init__.py
swedish_market_insights/constants.py
swedish_market_insights/inside_trades.py
swedish_market_insights/short_positions.py
swedish_market_insights/soup_utils.py
swedish_market_insights/utils.py
swedish_market_insights-0.3.0.dist-info/METADATA
swedish_market_insights-0.3.0.dist-info/WHEEL
swedish_market_insights-0.3.0.dist-info/RECORD
