Metadata-Version: 2.1
Name: swedish-market-insights
Version: 0.3.0
Summary: Package to scrape the Finansinspektion's registers
Home-page: https://github.com/fritjof-b/swedish-market-insights
License: MIT
Author: Fritjof Bengtsson
Author-email: fritjof.folkeson@gmail.com
Requires-Python: >=3.9,<4.0
Classifier: License :: OSI Approved :: MIT License
Classifier: Programming Language :: Python :: 3
Classifier: Programming Language :: Python :: 3.9
Classifier: Programming Language :: Python :: 3.10
Classifier: Programming Language :: Python :: 3.11
Requires-Dist: beautifulsoup4 (>=4.12.2,<5.0.0)
Requires-Dist: odfpy (>=1.4.1,<2.0.0)
Requires-Dist: pandas (>=2.0.1,<3.0.0)
Requires-Dist: requests (==2.28.2)
Project-URL: Repository, https://github.com/fritjof-b/swedish-market-insights
